[
    { "pattern": "open paren", "replacement": "(" },
    { "pattern": "close paren", "replacement": ")" },
    { "pattern": "open bracket", "replacement": "[" },
    { "pattern": "close bracket", "replacement": "]" },
    { "pattern": "open brace", "replacement": "{" },
    { "pattern": "close brace", "replacement": "}" },
    { "pattern": "period", "replacement": "." },
    { "pattern": "dot", "replacement": "." },
    { "pattern": "comma", "replacement": "," },
    { "pattern": "colon", "replacement": ":" },
    { "pattern": "semicolon", "replacement": ";" },
    { "pattern": "question mark", "replacement": "?" },
    { "pattern": "exclamation mark", "replacement": "!" },
    { "pattern": "apostrophe", "replacement": "'" },
    { "pattern": "single quote", "replacement": "'" },
    { "pattern": "double quote", "replacement": "\"" },
    { "pattern": "quotation mark", "replacement": "\"" },
    { "pattern": "ellipsis", "replacement": "…" },
    { "pattern": "hyphen", "replacement": "-" },
    { "pattern": "dash", "replacement": "—" },
    { "pattern": "underscore", "replacement": "_" },
    { "pattern": "dunder", "replacement": "__" },
    { "pattern": "double underscore", "replacement": "__" },
    { "pattern": "forward slash", "replacement": "/" },
    { "pattern": "backslash", "replacement": "\\" },
    { "pattern": "vertical bar", "replacement": "|" },
    { "pattern": "at sign", "replacement": "@" },
    { "pattern": "hash", "replacement": "#" },
    { "pattern": "percent", "replacement": "%" },
    { "pattern": "caret", "replacement": "^" },
    { "pattern": "ampersand", "replacement": "&" },
    { "pattern": "asterisk", "replacement": "*" },
    { "pattern": "plus", "replacement": "+" },
    { "pattern": "equals", "replacement": "=" },
    { "pattern": "less than", "replacement": "<" },
    { "pattern": "greater than", "replacement": ">" },
    { "pattern": "tilde", "replacement": "~" },
    { "pattern": "grave accent", "replacement": "`" }
  ]